taskqueue/__init__.py
taskqueue/py.typed
taskqueue-0.0.0.dist-info/LICENSE
taskqueue-0.0.0.dist-info/WHEEL
taskqueue-0.0.0.dist-info/METADATA
taskqueue-0.0.0.dist-info/RECORD
