Metadata-Version: 2.1
Name: taskqueue
Version: 0.0.0
Summary: An awesome package is coming soon! 🎉
Home-page: https://github.com/Kludex/taskqueue
License: MIT
Author: Marcelo Trylesinski
Author-email: marcelotryle@gmail.com
Requires-Python: >=3.8,<4.0
Classifier: Intended Audience :: Developers
Classifier: License :: OSI Approved :: MIT License
Classifier: Operating System :: OS Independent
Classifier: Programming Language :: Python
Classifier: Programming Language :: Python :: 3
Classifier: Programming Language :: Python :: 3 :: Only
Classifier: Programming Language :: Python :: 3.10
Classifier: Programming Language :: Python :: 3.8
Classifier: Programming Language :: Python :: 3.9
Classifier: Topic :: Software Development :: Libraries :: Python Modules
Project-URL: Repository, https://github.com/Kludex/taskqueue
